thetiscore.cpython-311-x86_64-linux-gnu.so
thetiscore.build/.gitignore
thetiscore-0.2.4.dist-info/METADATA
thetiscore-0.2.4.dist-info/WHEEL
thetiscore-0.2.4.dist-info/top_level.txt
thetiscore-0.2.4.dist-info/RECORD
thetiscore-0.2.4.dist-info/licenses/ATTRIBUTIONS.md
thetiscore-0.2.4.dist-info/licenses/LICENSE.md
thetiscore-0.2.4.dist-info/licenses/thirdparty-licenses/Jinja2-3.1.6/LICENSE.txt
thetiscore-0.2.4.dist-info/licenses/thirdparty-licenses/MarkupSafe-3.0.2/LICENSE.txt
thetiscore-0.2.4.dist-info/licenses/thirdparty-licenses/Nuitka-2.7.3/LICENSE.txt
thetiscore-0.2.4.dist-info/licenses/thirdparty-licenses/PyYAML-6.0.2/LICENSE
thetiscore-0.2.4.dist-info/licenses/thirdparty-licenses/Pygments-2.19.1/LICENSE
thetiscore-0.2.4.dist-info/licenses/thirdparty-licenses/Python-3.10.0/LICENSE.txt
thetiscore-0.2.4.dist-info/licenses/thirdparty-licenses/Python-3.10.12/LICENSE.txt
thetiscore-0.2.4.dist-info/licenses/thirdparty-licenses/certifi-2025.7.9/LICENSE
thetiscore-0.2.4.dist-info/licenses/thirdparty-licenses/certifi-2025.7.9/MPL-2.0.txt
thetiscore-0.2.4.dist-info/licenses/thirdparty-licenses/charset-normalizer-3.4.2/LICENSE
thetiscore-0.2.4.dist-info/licenses/thirdparty-licenses/contourpy-1.3.2/LICENSE
thetiscore-0.2.4.dist-info/licenses/thirdparty-licenses/cycler-0.12.1/LICENSE
thetiscore-0.2.4.dist-info/licenses/thirdparty-licenses/docutils-0.20.1/BSD-2-Clause.txt
thetiscore-0.2.4.dist-info/licenses/thirdparty-licenses/docutils-0.20.1/COPYING.txt
thetiscore-0.2.4.dist-info/licenses/thirdparty-licenses/docutils-0.20.1/python-2-1-1.txt
thetiscore-0.2.4.dist-info/licenses/thirdparty-licenses/idna-3.10/LICENSE.md
thetiscore-0.2.4.dist-info/licenses/thirdparty-licenses/importlib_metadata-8.7.0/LICENSE
thetiscore-0.2.4.dist-info/licenses/thirdparty-licenses/joblib-1.5.0/LICENSE.txt
thetiscore-0.2.4.dist-info/licenses/thirdparty-licenses/kiwisolver-1.4.8/LICENSE
thetiscore-0.2.4.dist-info/licenses/thirdparty-licenses/matplotlib-3.10.3/LICENSE
thetiscore-0.2.4.dist-info/licenses/thirdparty-licenses/matplotlib-3.10.3/LICENSE_AMSFONTS
thetiscore-0.2.4.dist-info/licenses/thirdparty-licenses/matplotlib-3.10.3/LICENSE_BAKOMA
thetiscore-0.2.4.dist-info/licenses/thirdparty-licenses/matplotlib-3.10.3/LICENSE_CARLOGO
thetiscore-0.2.4.dist-info/licenses/thirdparty-licenses/matplotlib-3.10.3/LICENSE_COLORBREWER
thetiscore-0.2.4.dist-info/licenses/thirdparty-licenses/matplotlib-3.10.3/LICENSE_COURIERTEN
thetiscore-0.2.4.dist-info/licenses/thirdparty-licenses/matplotlib-3.10.3/LICENSE_JSXTOOLS_RESIZE_OBSERVER
thetiscore-0.2.4.dist-info/licenses/thirdparty-licenses/matplotlib-3.10.3/LICENSE_QHULL
thetiscore-0.2.4.dist-info/licenses/thirdparty-licenses/matplotlib-3.10.3/LICENSE_QT4_EDITOR
thetiscore-0.2.4.dist-info/licenses/thirdparty-licenses/matplotlib-3.10.3/LICENSE_SOLARIZED
thetiscore-0.2.4.dist-info/licenses/thirdparty-licenses/matplotlib-3.10.3/LICENSE_STIX
thetiscore-0.2.4.dist-info/licenses/thirdparty-licenses/matplotlib-3.10.3/LICENSE_YORICK
thetiscore-0.2.4.dist-info/licenses/thirdparty-licenses/ntplib-0.4.0/LICENSE.txt
thetiscore-0.2.4.dist-info/licenses/thirdparty-licenses/numpy-2.2.6/LICENSE.txt
thetiscore-0.2.4.dist-info/licenses/thirdparty-licenses/numpy-2.2.6/LICENSE_linux.txt
thetiscore-0.2.4.dist-info/licenses/thirdparty-licenses/packaging-25.0/LICENSE
thetiscore-0.2.4.dist-info/licenses/thirdparty-licenses/packaging-25.0/LICENSE.APACHE
thetiscore-0.2.4.dist-info/licenses/thirdparty-licenses/packaging-25.0/LICENSE.BSD
thetiscore-0.2.4.dist-info/licenses/thirdparty-licenses/pandas-2.2.3/LICENSE
thetiscore-0.2.4.dist-info/licenses/thirdparty-licenses/pandas-2.2.3/LICENSE_linux
thetiscore-0.2.4.dist-info/licenses/thirdparty-licenses/pillow-11.2.1/LICENSE
thetiscore-0.2.4.dist-info/licenses/thirdparty-licenses/pillow-11.2.1/LICENSE_linux
thetiscore-0.2.4.dist-info/licenses/thirdparty-licenses/pillow-11.2.1/README.ijg
thetiscore-0.2.4.dist-info/licenses/thirdparty-licenses/pycryptodome-3.23.0/LICENSE.rst
thetiscore-0.2.4.dist-info/licenses/thirdparty-licenses/pyparsing-3.2.3/LICENSE
thetiscore-0.2.4.dist-info/licenses/thirdparty-licenses/python-dateutil-2.9.0.post0/LICENSE
thetiscore-0.2.4.dist-info/licenses/thirdparty-licenses/pytz-2025.2/LICENSE.txt
thetiscore-0.2.4.dist-info/licenses/thirdparty-licenses/reportlab-4.0.7/LICENSE
thetiscore-0.2.4.dist-info/licenses/thirdparty-licenses/requests-2.32.4/LICENSE
thetiscore-0.2.4.dist-info/licenses/thirdparty-licenses/rst2pdf-0.102/LICENSE.txt
thetiscore-0.2.4.dist-info/licenses/thirdparty-licenses/scikit-learn-1.6.1/COPYING
thetiscore-0.2.4.dist-info/licenses/thirdparty-licenses/scikit-learn-1.6.1/COPYING_linux
thetiscore-0.2.4.dist-info/licenses/thirdparty-licenses/scipy-1.15.3/LICENSE.txt
thetiscore-0.2.4.dist-info/licenses/thirdparty-licenses/scipy-1.15.3/LICENSE_linux.txt
thetiscore-0.2.4.dist-info/licenses/thirdparty-licenses/setuptools-80.8.0/LICENSE
thetiscore-0.2.4.dist-info/licenses/thirdparty-licenses/six-1.17.0/LICENSE
thetiscore-0.2.4.dist-info/licenses/thirdparty-licenses/smartypants-2.0.1/COPYING
thetiscore-0.2.4.dist-info/licenses/thirdparty-licenses/strictyaml-1.7.3/LICENSE.txt
thetiscore-0.2.4.dist-info/licenses/thirdparty-licenses/threadpoolctl-3.6.0/LICENSE
thetiscore-0.2.4.dist-info/licenses/thirdparty-licenses/typing_extensions-4.13.2/LICENSE
thetiscore-0.2.4.dist-info/licenses/thirdparty-licenses/urllib3-2.5.0/LICENSE.txt
thetiscore-0.2.4.dist-info/licenses/thirdparty-licenses/zipp-3.21.0/LICENSE
thetiscore-0.2.4.dist-info/licenses/thirdparty-licenses/zstandard-0.23.0/LICENSE
